pew/__init__.py
PewPew_10_Emulator-0.3.dist-info/LICENCE
PewPew_10_Emulator-0.3.dist-info/METADATA
PewPew_10_Emulator-0.3.dist-info/WHEEL
PewPew_10_Emulator-0.3.dist-info/top_level.txt
PewPew_10_Emulator-0.3.dist-info/RECORD
